gradle.properties
hexdoc_hexways/__gradle_version__.py
hexdoc_hexways/__init__.py
hexdoc_hexways/__version__.py
hexdoc_hexways/_hooks.py
hexdoc_hexways/py.typed
hexdoc_hexways/_export/.gitignore
hexdoc_hexways/_export/__init__.py
hexdoc_hexways/_export/generated/__init__.py
hexdoc_hexways/_export/generated/hexways.hexdoc.json
hexdoc_hexways/_export/generated/hexways.patterns.hexdoc.json
hexdoc_hexways/_export/generated/assets/hexcasting/patchouli_books/thehexbook/en_us/entries/patterns/spells/hexways.json
hexdoc_hexways/_export/generated/assets/hexways/lang/en_us.flatten.json5
hexdoc_hexways/_export/generated/assets/hexways/lang/en_us.json
hexdoc_hexways/_export/generated/assets/hexways/lang/zh_cn.flatten.json5
hexdoc_hexways/_export/generated/assets/hexways/lang/zh_cn.json
hexdoc_hexways/_export/generated/assets/hexways/textures/StickiaIconV2smol.png
hexdoc_hexways/_export/generated/data/hexcasting/tags/action/per_world_pattern.json
hexdoc_hexways/_templates/__init__.py
hexdoc_hexways-1.0.1.1.0.dist-info/METADATA
hexdoc_hexways-1.0.1.1.0.dist-info/WHEEL
hexdoc_hexways-1.0.1.1.0.dist-info/entry_points.txt
hexdoc_hexways-1.0.1.1.0.dist-info/licenses/LICENSE
hexdoc_hexways-1.0.1.1.0.dist-info/RECORD
