Metadata-Version: 2.4
Name: hexdoc-hexways
Version: 1.0.1.1.0
Summary: Portal Hex Addon addon for Hex Casting
Project-URL: Homepage, https://shadowcube264.github.io/hexways-1.20.1
Project-URL: Source, https://github.com/ShadowCube264/hexways-1.20.1
Author: ShadowCube264
License-File: LICENSE
Keywords: hexdoc
Requires-Python: >=3.12
Requires-Dist: hexdoc-hexcasting~=0.11.2.1.0
